django_inventare_staticfiles/__init__.py
django_inventare_staticfiles/apps.py
django_inventare_staticfiles/finders.py
django_inventare_staticfiles/templatetags/__init__.py
django_inventare_staticfiles/templatetags/remote_url.py
django_inventare_staticfiles-0.0.7.dist-info/LICENSE
django_inventare_staticfiles-0.0.7.dist-info/METADATA
django_inventare_staticfiles-0.0.7.dist-info/WHEEL
django_inventare_staticfiles-0.0.7.dist-info/top_level.txt
django_inventare_staticfiles-0.0.7.dist-info/RECORD
